iobm/__init__.py
iobm/cgan_generate.py
iobm/cgan_train.py
iobm/container/__init__.py
iobm/container/configs.py
iobm/container/core.py
iobm/container/data.py
iobm/container/models.py
iobm-1/__init__.py
iobm-1/cgan_generate.py
iobm-1/cgan_train.py
iobm-1/container/__init__.py
iobm-1/container/configs.py
iobm-1/container/core.py
iobm-1/container/data.py
iobm-1/container/models.py
iobm-2/__init__.py
iobm-2/cgan_generate.py
iobm-2/cgan_train.py
iobm-2/container/__init__.py
iobm-2/container/configs.py
iobm-2/container/core.py
iobm-2/container/data.py
iobm-2/container/models.py
iobm-0.5.4.dist-info/LICENSE
iobm-0.5.4.dist-info/METADATA
iobm-0.5.4.dist-info/WHEEL
iobm-0.5.4.dist-info/entry_points.txt
iobm-0.5.4.dist-info/top_level.txt
iobm-0.5.4.dist-info/RECORD
