Metadata-Version: 2.1
Name: iobm
Version: 0.5.4
Summary: A simple conditional adverserial neural network module.
Home-page: https://github.com/MJ-GITHUB-007/cGAN
Author: Mohammed Junaid
Author-email: junaid1607@outlook.com
License: MIT
Project-URL: GitHub, https://github.com/MJ-GITHUB-007/cGAN
Classifier: Programming Language :: Python :: 3
Classifier: License :: OSI Approved :: MIT License
Classifier: Operating System :: OS Independent
Requires-Python: >=3.6
License-File: LICENSE
Requires-Dist: Pillow
Requires-Dist: torch
Requires-Dist: torchvision
Requires-Dist: tqdm
